libsrg_log2web/Demo.py
libsrg_log2web/FlaskApp.py
libsrg_log2web/Log2Web.py
libsrg_log2web/LoggerGUIProxy.py
libsrg_log2web/__init__.py
libsrg_log2web/static/style.css
libsrg_log2web/templates/status.html
libsrg_log2web-1.1.0.dist-info/METADATA
libsrg_log2web-1.1.0.dist-info/WHEEL
libsrg_log2web-1.1.0.dist-info/top_level.txt
libsrg_log2web-1.1.0.dist-info/RECORD
