Metadata-Version: 2.4
Name: libsrg_log2web
Version: 1.1.0
Summary: Multithreded logging to webpage
Author-email: Steve Goncalo <steven@goncalo.us>
License-Expression: MIT
Classifier: Programming Language :: Python :: 3.14
Classifier: Development Status :: 5 - Production/Stable
Classifier: Operating System :: POSIX :: Linux
Classifier: Natural Language :: English
Classifier: Topic :: Utilities
Classifier: Intended Audience :: Developers
Requires-Python: >=3.14
Requires-Dist: flask>=3.1.2
Requires-Dist: libsrg>=6.0.4
